kaviyes/util/__file_util__.py
kaviyes/util/__init__.py
kaviyes/util/__std_util__.py
kaviyes/util/legacy/__init__.py
kaviyes/util/legacy/__legacy_util__.py
kaviyesutil-2.1.2.dist-info/LICENSE
kaviyesutil-2.1.2.dist-info/METADATA
kaviyesutil-2.1.2.dist-info/WHEEL
kaviyesutil-2.1.2.dist-info/top_level.txt
kaviyesutil-2.1.2.dist-info/RECORD
