Metadata-Version: 2.1
Name: kaviyesutil
Version: 2.1.2
Summary: A standard kaviyes utility for python thats ideal for small projects and prototypes.
Home-page: https://github.com/Kaviyes/kaviyesutil
Author: Kaviyes
Author-email: contact.karlvince@gmail.com
License: MIT
Keywords: utility,toolkit
Classifier: Development Status :: 3 - Alpha
Classifier: Intended Audience :: Developers
Classifier: License :: OSI Approved :: MIT License
Classifier: Programming Language :: Python :: 3
Classifier: Programming Language :: Python :: 3.11
Classifier: Operating System :: Microsoft :: Windows
Classifier: Operating System :: POSIX :: Linux
Classifier: Operating System :: MacOS :: MacOS X
Requires-Python: >=3.9
License-File: LICENSE
Requires-Dist: requests
